Metadata-Version: 2.1
Name: bofh
Version: 0.9.8
Summary: Cerebrum bofh client
Home-page: https://github.com/unioslo/pybofh
Author: USIT, University of Oslo
Author-email: bnt-int@usit.uio.no
License: GPLv3
Keywords: cerebrum bofh xmlrpc client
Classifier: Development Status :: 4 - Beta
Classifier: Environment :: Console
Classifier: Intended Audience :: System Administrators
Classifier: License :: OSI Approved :: GNU General Public License v3 (GPLv3)
Classifier: Programming Language :: Python :: 2.7
Classifier: Programming Language :: Python :: 3.6
Classifier: Programming Language :: Python :: 3.7
Classifier: Programming Language :: Python :: 3.8
Classifier: Programming Language :: Python :: 3.9
Classifier: Topic :: Software Development :: Libraries
Classifier: Topic :: System :: Systems Administration
License-File: COPYING
